nerfprobe_core/__init__.py
nerfprobe_core/core/__init__.py
nerfprobe_core/core/entities.py
nerfprobe_core/core/gateway.py
nerfprobe_core/core/scorer.py
nerfprobe_core/models/__init__.py
nerfprobe_core/models/models.yaml
nerfprobe_core/models/research.py
nerfprobe_core/probes/__init__.py
nerfprobe_core/probes/config.py
nerfprobe_core/probes/advanced/__init__.py
nerfprobe_core/probes/advanced/consistency_probe.py
nerfprobe_core/probes/advanced/constraint_probe.py
nerfprobe_core/probes/advanced/context_probe.py
nerfprobe_core/probes/advanced/cot_probe.py
nerfprobe_core/probes/advanced/fingerprint_probe.py
nerfprobe_core/probes/advanced/json_probe.py
nerfprobe_core/probes/advanced/logic_probe.py
nerfprobe_core/probes/advanced/repetition_probe.py
nerfprobe_core/probes/advanced/routing_probe.py
nerfprobe_core/probes/core/__init__.py
nerfprobe_core/probes/core/code_probe.py
nerfprobe_core/probes/core/fact_probe.py
nerfprobe_core/probes/core/math_probe.py
nerfprobe_core/probes/core/style_probe.py
nerfprobe_core/probes/core/timing_probe.py
nerfprobe_core/probes/optional/__init__.py
nerfprobe_core/probes/optional/calibration_probe.py
nerfprobe_core/probes/optional/multilingual_probe.py
nerfprobe_core/probes/optional/zeroprint_probe.py
nerfprobe_core/scorers/__init__.py
nerfprobe_core/scorers/calibration.py
nerfprobe_core/scorers/code.py
nerfprobe_core/scorers/consistency_scorer.py
nerfprobe_core/scorers/constraint.py
nerfprobe_core/scorers/cot.py
nerfprobe_core/scorers/entropy.py
nerfprobe_core/scorers/fact_scorer.py
nerfprobe_core/scorers/json_scorer.py
nerfprobe_core/scorers/logic.py
nerfprobe_core/scorers/math.py
nerfprobe_core/scorers/multilingual.py
nerfprobe_core/scorers/repetition.py
nerfprobe_core/scorers/ttr.py
nerfprobe_core-0.2.0.dist-info/METADATA
nerfprobe_core-0.2.0.dist-info/WHEEL
nerfprobe_core-0.2.0.dist-info/licenses/LICENSE
nerfprobe_core-0.2.0.dist-info/RECORD
